PyGeomesh/__init__.py
PyGeomesh/box.py
PyGeomesh/cylinder.py
PyGeomesh/geometry.py
PyGeomesh/point.py
PyGeomesh/polygon.py
PyGeomesh/transform.py
pygeomesh-0.1.1.dist-info/LICENSE
pygeomesh-0.1.1.dist-info/METADATA
pygeomesh-0.1.1.dist-info/WHEEL
pygeomesh-0.1.1.dist-info/top_level.txt
pygeomesh-0.1.1.dist-info/RECORD
