Metadata-Version: 2.1
Name: pygeomesh
Version: 0.1.1
Summary: PyGeomesh is a tool for generating discretized points from geometry.
Home-page: https://github.com/AndPuQing/PyGeomesh
Author: PuQing
Author-email: me@puqing.work
License: Apache License 2.0
Download-URL: https://pypi.python.org/pypi/pygeomesh
Platform: any
Classifier: Development Status :: 4 - Beta
Classifier: License :: OSI Approved :: Apache Software License
Classifier: Intended Audience :: Science/Research
Classifier: Operating System :: OS Independent
Classifier: Programming Language :: Python :: 3
Classifier: Topic :: Scientific/Engineering :: Mathematics
Requires: numpy
Requires: scipy
Requires: matplotlib
